tsk/__init__.py
tsk/_version.py
tsk-0.1.0.dist-info/LICENSE
tsk-0.1.0.dist-info/METADATA
tsk-0.1.0.dist-info/WHEEL
tsk-0.1.0.dist-info/entry_points.txt
tsk-0.1.0.dist-info/top_level.txt
tsk-0.1.0.dist-info/RECORD
