Metadata-Version: 2.1
Name: tsk
Version: 0.1.0
Summary: Notify the user when a command completes.
Author-email: Alex Lowe <alex@lowe.dev>
Project-URL: Homepage, https://github.com/lengau/tsk
Project-URL: Issues, https://github.com/lengau/tsk/issues
Classifier: Development Status :: 4 - Beta
Classifier: Environment :: Console
Classifier: Intended Audience :: End Users/Desktop
Classifier: License :: OSI Approved :: GNU General Public License v3 (GPLv3)
Classifier: Programming Language :: Python :: 3
Classifier: Operating System :: POSIX :: Linux
Requires-Python: >=3.10
License-File: LICENSE
